metaflow_extensions/ollama/plugins/constants.py
metaflow_extensions/ollama/plugins/exceptions.py
metaflow_extensions/ollama/plugins/mfextinit_ollama.py
metaflow_extensions/ollama/plugins/ollama.py
metaflow_extensions/ollama/plugins/ollama_decorator.py
metaflow_ollama-0.1.1.dist-info/LICENSE
metaflow_ollama-0.1.1.dist-info/METADATA
metaflow_ollama-0.1.1.dist-info/WHEEL
metaflow_ollama-0.1.1.dist-info/top_level.txt
metaflow_ollama-0.1.1.dist-info/RECORD
