Metadata-Version: 2.1
Name: metaflow-ollama
Version: 0.1.1
Summary: An EXPERIMENTAL Ollama decorator for Metaflow
Author: Outerbounds
Author-email: hello@outerbounds.co
Classifier: Development Status :: 3 - Alpha
Classifier: Intended Audience :: Developers
Classifier: Programming Language :: Python :: 3
Classifier: Programming Language :: Python :: 3.6
Classifier: Programming Language :: Python :: 3.7
Classifier: Programming Language :: Python :: 3.8
Classifier: Programming Language :: Python :: 3.9
Classifier: Programming Language :: Python :: 3.10
Classifier: Programming Language :: Python :: 3.11
Requires-Python: >=3.6
License-File: LICENSE
